super_terminal/__init__.py
super_terminal/__main__.py
super_terminal/agent_manager.py
super_terminal/app.py
super_terminal/workspace_manager.py
super_terminal_tui-0.1.1.dist-info/licenses/LICENSE
super_terminal_tui-0.1.1.dist-info/METADATA
super_terminal_tui-0.1.1.dist-info/WHEEL
super_terminal_tui-0.1.1.dist-info/entry_points.txt
super_terminal_tui-0.1.1.dist-info/top_level.txt
super_terminal_tui-0.1.1.dist-info/RECORD
