Metadata-Version: 2.4
Name: super-terminal-tui
Version: 0.1.1
Summary: A TUI application for managing multiple AI agents with isolated workspaces
Author-email: Kuldeep Paul <kuldeep.paul08@gmail.com>
License: MIT
Project-URL: Homepage, https://github.com/yourusername/super-terminal
Project-URL: Documentation, https://github.com/yourusername/super-terminal#readme
Project-URL: Repository, https://github.com/yourusername/super-terminal
Project-URL: Issues, https://github.com/yourusername/super-terminal/issues
Keywords: terminal,tui,ai,agents,multi-agent,workspace,textual
Classifier: Development Status :: 4 - Beta
Classifier: Intended Audience :: Developers
Classifier: License :: OSI Approved :: MIT License
Classifier: Programming Language :: Python :: 3
Classifier: Programming Language :: Python :: 3.8
Classifier: Programming Language :: Python :: 3.9
Classifier: Programming Language :: Python :: 3.10
Classifier: Programming Language :: Python :: 3.11
Classifier: Programming Language :: Python :: 3.12
Classifier: Operating System :: OS Independent
Classifier: Topic :: Terminals
Classifier: Topic :: Software Development :: User Interfaces
Requires-Python: >=3.8
License-File: LICENSE
Requires-Dist: textual>=0.47.0
Requires-Dist: pyte>=0.8.1
Requires-Dist: rich<14.0.0,>=13.7.0
Requires-Dist: watchdog>=3.0.0
Provides-Extra: dev
Requires-Dist: pytest>=7.0.0; extra == "dev"
Requires-Dist: black>=23.0.0; extra == "dev"
Requires-Dist: mypy>=1.0.0; extra == "dev"
Dynamic: license-file
